custom_cytomine_client/__init__.py
custom_cytomine_client/converter.py
custom_cytomine_client/interface/__init__.py
custom_cytomine_client/interface/converter.py
custom_cytomine_client/object/__init__.py
custom_cytomine_client/object/converter.py
custom_cytomine_client/util/__init__.py
custom_cytomine_client/util/custom_exception.py
custom_cytomine_client/util/fit_util.py
custom_cytomine_client/util/normal_util.py
custom_cytomine_client-0.1.1.dist-info/METADATA
custom_cytomine_client-0.1.1.dist-info/WHEEL
custom_cytomine_client-0.1.1.dist-info/RECORD
