Metadata-Version: 2.1
Name: custom-cytomine-client
Version: 0.1.1
Summary: Custom Cytomine client for Python
Author: punrabbit
Author-email: tjdmsch2201@gmail.com
Requires-Python: >=3.10,<4.0
Classifier: Programming Language :: Python :: 3
Classifier: Programming Language :: Python :: 3.10
Classifier: Programming Language :: Python :: 3.11
Classifier: Programming Language :: Python :: 3.12
Requires-Dist: annotated-types (==0.6.0)
Requires-Dist: black (==24.3.0)
Requires-Dist: cytomine-python-client (==2.4.0)
Requires-Dist: future (==1.0.0)
Requires-Dist: httpcore (==0.17.3)
Requires-Dist: httpx (==0.24.1)
Requires-Dist: mypy-extensions (==1.0.0)
Requires-Dist: numpy (==1.26.4)
Requires-Dist: opencv-python-headless (==4.9.0.80)
Requires-Dist: overrides (==7.7.0)
Requires-Dist: pillow (==10.3.0)
Requires-Dist: pydantic (==2.6.4)
Requires-Dist: pydantic-core (==2.16.3)
Requires-Dist: requests (==2.31.0)
Requires-Dist: tomli (==2.0.1)
Requires-Dist: tomlkit (==0.12.4)
Requires-Dist: tqdm (==4.66.2)
Requires-Dist: typing-extensions (==4.10.0)
Requires-Dist: xmltodict (==0.13.0)
